http_csp/__init__.py
http_csp/csp.py
http_csp-1.0.0.dist-info/LICENSE
http_csp-1.0.0.dist-info/METADATA
http_csp-1.0.0.dist-info/WHEEL
http_csp-1.0.0.dist-info/RECORD
