Metadata-Version: 2.1
Name: http-csp
Version: 1.0.0
Summary: HTTP Content Security Policy Manager
License: MIT
Author: Jacky Lam
Author-email: jacky.lam@r2studiohk.com
Requires-Python: >=3.9
Classifier: License :: OSI Approved :: MIT License
Classifier: Programming Language :: Python :: 3
Classifier: Programming Language :: Python :: 3.9
Classifier: Programming Language :: Python :: 3.10
Classifier: Programming Language :: Python :: 3.11
Classifier: Programming Language :: Python :: 3.12
Project-URL: repository, https://github.com/jackylamhk/python-http-csp
